{
    "@context": "https://standards-ontotest.oftrust.net/v2/Context/Identity/Element/BuildingElement/Floor/",
    "@type": "Floor",
    "@id": "",
    "data": {
        "areaGross": "",
        "url": "",
        "ifcElementType": "",
        "colorCode": "",
        "categorizationLocal": "",
        "thickness": "",
        "ifcGuid": "",
        "ifcElementName": "",
        "length": "",
        "width": "",
        "areaNet": "",
        "status": "",
        "weight": "",
        "descriptionGeneral": "",
        "volume": "",
        "height": "",
        "name": "",
        "idLocal": "",
        "colorName": ""
    },
    "metadata": {
        "updatedAt": "",
        "createdAt": "",
        "updatedBy": "",
        "createdBy": ""
    }
}