{
    "@context": "https://standards-ontotest.oftrust.net/v2andards/v2/Context/Identity/Equipment/Device/Sensor/CarbonDioxideSensor/",
    "@type": "CarbonDioxideSensor",
    "@id": "",
    "data": {
        "ifcElementName": "",
        "volume": "",
        "name": "",
        "areaGross": "",
        "length": "",
        "serialNumber": "",
        "power": "",
        "url": "",
        "idLocal": "",
        "installationTypeAvailable": "",
        "installationType": "",
        "width": "",
        "ifcElementType": "",
        "thickness": "",
        "industryDomain": "",
        "typeName": "",
        "electricityCurrent": "",
        "categorizationLocal": "",
        "colorCode": "",
        "areaNet": "",
        "status": "",
        "descriptionGeneral": "",
        "colorName": "",
        "ifcGuid": "",
        "height": "",
        "weight": "",
        "categorizationETIM": ""
    },
    "metadata": {
        "createdAt": "",
        "createdBy": "",
        "updatedBy": "",
        "updatedAt": ""
    },
    "function": ""
}