{
    "$schema": "http://json-schema.org/draft-07/schema",
    "type": "object",
    "properties": {
        "@context": {
            "type": "string",
            "minLength": 1,
            "const": "https://standards-ontotest.oftrust.net/v2/Context/Identity/Process/Measure/"
        },
        "@type": {
            "type": "string",
            "minLength": 1,
            "enum": [
                "Measure"
            ],
            "const": "Measure"
        },
        "function": {
            "title": "",
            "description": "",
            "type": "string"
        },
        "locationName": {
            "title": "",
            "description": "",
            "type": "string"
        },
        "data": {
            "title": "",
            "description": "",
            "type": "object",
            "properties": {
                "duration": {
                    "title": "Duration",
                    "description": "Duration (time)",
                    "type": "string"
                },
                "nameLocal": {
                    "title": "Local name",
                    "description": "Local name",
                    "type": "string"
                },
                "status": {
                    "title": "Life-cycle status",
                    "description": "Life-cycle status",
                    "type": "string"
                },
                "descriptionGeneral": {
                    "title": "Description",
                    "description": "Description",
                    "type": "string"
                },
                "endDateTime": {
                    "title": "End time",
                    "description": "End time",
                    "type": "string"
                },
                "processTypePoT": {
                    "title": "Process type - PoT type",
                    "description": "PoT defined standard process type",
                    "type": "string"
                },
                "processValue": {
                    "title": "Output value",
                    "description": "Output value of the process",
                    "type": "string"
                },
                "idLocal": {
                    "title": "Local identifier",
                    "description": "Locally given identifier",
                    "type": "string"
                },
                "startDateTime": {
                    "title": "Start time",
                    "description": "Start time",
                    "type": "string"
                },
                "executor": {
                    "title": "Process executor",
                    "description": "Executor of the process (source of the data)",
                    "type": "string"
                }
            }
        },
        "metadata": {
            "title": "Metadata",
            "description": "Metadata container",
            "type": "object",
            "properties": {
                "updatedAt": {
                    "title": "Update time",
                    "description": "Time when the data is updated",
                    "type": "string"
                },
                "updatedBy": {
                    "title": "Updater",
                    "description": "Updater of an identity",
                    "type": "string"
                },
                "createdBy": {
                    "title": "Creator",
                    "description": "Creator of and identity",
                    "type": "string"
                },
                "createdAt": {
                    "title": "Creation time",
                    "description": "Time when the data is created",
                    "type": "string"
                }
            }
        },
        "executor": {
            "title": "",
            "description": "",
            "type": "string"
        },
        "@id": {
            "title": "",
            "description": "",
            "type": "string"
        }
    },
    "required": [
        "data",
        "@context",
        "@type",
        "@id"
    ]
}